{"created_at": "Tue Oct 18 00:35:33 +0000 2011", "favorited": false, "hashtags": ["Windows", "Microsoft", "Windows", "Appl"], "id": 126094027140513792, "lang": "en", "retweeted": false, "source": "<a href=\"http://www.f8ball.com/f8ball/\" rel=\"nofollow\">f8ball</a>", "text": "POLL: http://t.co/tZBleGaQ Q:Should @Microsoft consider making its own hardware for #Windows like @Apple does? #Microsoft #Windows #Appl ...", "truncated": false, "urls": {"http://t.co/tZBleGaQ": "http://bit.ly/oYGTWN"}, "user": {"created_at": "Thu Oct 07 21:22:53 +0000 2010", "followers_count": 347, "friends_count": 1886, "geo_enabled": true, "id": 199843649, "lang": "en", "listed_count": 9, "location": "Washington D.C.", "name": "f8ball", "profile_background_color": "C0DEED", "profile_background_image_url": "http://abs.twimg.com/images/themes/theme1/bg.png", "profile_background_tile": false, "profile_image_url": "https://pbs.twimg.com/profile_images/1386103106/248057_201910349851879_157298484313066_559566_6796027_n_normal.jpg", "profile_link_color": "0084B4", "profile_sidebar_fill_color": "DDEEF6", "profile_text_color": "333333", "protected": false, "screen_name": "f8ball", "statuses_count": 9244, "url": "http://t.co/NJDQVzfhil"}, "user_mentions": [{"id": 74286565, "name": "Microsoft", "screen_name": "Microsoft"}, {"id": 380749300, "name": "@apple", "screen_name": "Apple"}]}