{"created_at": "Tue Oct 18 13:08:13 +0000 2011", "favorited": false, "hashtags": ["tsk"], "id": 126283440457912320, "lang": "en", "retweeted": false, "source": "<a href=\"http://twitter.com\" rel=\"nofollow\">Twitter Web Client</a>", "text": "Hello again, iPhone 4!!! Thank you, @apple! Although this should have never broken in the first place! #tsk", "truncated": false, "user": {"created_at": "Sat Apr 04 11:16:08 +0000 2009", "description": "Groove is in the heart.", "favourites_count": 1076, "followers_count": 629, "friends_count": 404, "id": 28776455, "lang": "en", "listed_count": 14, "location": "Manila, Philippines! ", "name": "Cecile Golez", "profile_background_color": "B2DFDA", "profile_background_image_url": "http://abs.twimg.com/images/themes/theme13/bg.gif", "profile_background_tile": false, "profile_banner_url": "https://pbs.twimg.com/profile_banners/28776455/1400048086", "profile_image_url": "https://pbs.twimg.com/profile_images/466461517106675712/gn3aSYL9_normal.jpeg", "profile_link_color": "93A644", "profile_sidebar_fill_color": "FFFFFF", "profile_text_color": "333333", "protected": false, "screen_name": "cez8", "statuses_count": 17280, "time_zone": "Hong Kong", "utc_offset": 28800}, "user_mentions": [{"id": 380749300, "name": "@apple", "screen_name": "Apple"}]}