{"created_at": "Tue Oct 18 14:25:37 +0000 2011", "favorited": false, "hashtags": ["TomCruise", "Siri"], "id": 126302918797312000, "lang": "en", "retweeted": false, "source": "<a href=\"http://twitter.com\" rel=\"nofollow\">Twitter Web Client</a>", "text": "Just when #TomCruise thought he had a unique name for his daughter, @Apple pulls the rug out from under him with the new #Siri App.", "truncated": false, "user": {"created_at": "Tue Oct 11 10:19:11 +0000 2011", "description": "Yipiii Twitter account for all things geek! Stay up to date with the lastest new, commentary and products in the world of geeks.", "followers_count": 439, "friends_count": 1107, "id": 388781550, "lang": "en", "listed_count": 2, "location": "London", "name": "Yipiii4Geeks", "profile_background_color": "161616", "profile_background_image_url": "http://abs.twimg.com/images/themes/theme15/bg.png", "profile_background_tile": false, "profile_image_url": "https://pbs.twimg.com/profile_images/1583088737/yipiii_bigger_reasonably_small_normal.jpg", "profile_link_color": "0056AB", "profile_sidebar_fill_color": "FFFFFF", "profile_text_color": "3D3D3D", "protected": false, "screen_name": "Yipiii4Geeks", "statuses_count": 88, "time_zone": "London", "url": "http://t.co/mVPCLN3eAW", "utc_offset": 3600}, "user_mentions": [{"id": 380749300, "name": "@apple", "screen_name": "Apple"}]}