{"coordinates": {"coordinates": [-107.3516404, 24.7916457], "type": "Point"}, "created_at": "Thu Oct 20 04:13:32 +0000 2011", "favorited": false, "geo": {"coordinates": [24.7916457, -107.3516404], "type": "Point"}, "hashtags": ["Twitter"], "id": 126873660442148865, "lang": "es", "place": {"attributes": {}, "bounding_box": {"coordinates": [[[-107.806281, 24.0281619], [-106.877832, 24.0281619], [-106.877832, 25.2968151], [-107.806281, 25.2968151]]], "type": "Polygon"}, "contained_within": [], "country": "M\u00e9xico", "country_code": "MX", "full_name": "Culiac\u00e1n, Sinaloa", "id": "22886de3634e157a", "name": "Culiac\u00e1n", "place_type": "city", "url": "https://api.twitter.com/1.1/geo/id/22886de3634e157a.json"}, "retweeted": false, "source": "<a href=\"http://twitter.com/download/iphone\" rel=\"nofollow\">Twitter for iPhone</a>", "text": "Creo k ya me saldre de #Twitter", "truncated": false, "user": {"created_at": "Fri Aug 14 16:49:39 +0000 2009", "description": "Da RT  o fav a mis tweets y te doy #follow #TFB #followback #followbackseguro.", "favourites_count": 381, "followers_count": 3477, "friends_count": 3827, "geo_enabled": true, "id": 65677856, "lang": "en", "listed_count": 6, "location": "culiacan, sin. ", "name": "Albert glez", "profile_background_color": "1A1B1F", "profile_background_image_url": "http://pbs.twimg.com/profile_background_images/65288712/culiacan.jpg", "profile_background_tile": false, "profile_banner_url": "https://pbs.twimg.com/profile_banners/65677856/1402210766", "profile_image_url": "https://pbs.twimg.com/profile_images/455558054906306560/dpaR4fWF_normal.jpeg", "profile_link_color": "2FC2EF", "profile_sidebar_fill_color": "252429", "profile_text_color": "666666", "protected": false, "screen_name": "albert_213", "statuses_count": 11017, "time_zone": "Mazatlan", "url": "https://t.co/BCbNnivdtP", "utc_offset": -21600}}